antelope_reports/__init__.py
antelope_reports/comparators.py
antelope_reports/gsheet_observer.py
antelope_reports/report.py
antelope_reports/charts/__init__.py
antelope_reports/charts/base.py
antelope_reports/charts/combi.py
antelope_reports/charts/contrib_lcia.py
antelope_reports/charts/model_graph.py
antelope_reports/charts/pos_neg.py
antelope_reports/charts/sensitivity_bars.py
antelope_reports/charts/simple.py
antelope_reports/charts/stackbar_compare.py
antelope_reports/charts/vertical.py
antelope_reports/charts/waterfall.py
antelope_reports/fg_builder/__init__.py
antelope_reports/fg_builder/ecoinvent_grids.py
antelope_reports/fg_builder/lca_study.py
antelope_reports/fg_builder/model_updater.py
antelope_reports/fg_builder/param_manager.py
antelope_reports/fg_builder/scenario_updater.py
antelope_reports/fg_builder/stage_manager.py
antelope_reports/kpi/__init__.py
antelope_reports/kpi/equivalency.py
antelope_reports/kpi/kpi.py
antelope_reports/lca_test/__init__.py
antelope_reports/lcia/__init__.py
antelope_reports/lcia/ecoinvent.py
antelope_reports/lcia/flow_comparator.py
antelope_reports/lcia/indicators.py
antelope_reports/lcia/lcia_eval.py
antelope_reports/lcia/screening.py
antelope_reports/lcia/traci.py
antelope_reports/lcia/worldsteel.py
antelope_reports/lcia/xlsx_lcia.py
antelope_reports/lcia/qdb_client/__init__.py
antelope_reports/lcia/qdb_client/qdb_client.py
antelope_reports/mfa_models/__init__.py
antelope_reports/mfa_models/conventions.py
antelope_reports/mfa_models/interface.py
antelope_reports/mfa_models/lca_model.py
antelope_reports/mfa_models/lca_study.py
antelope_reports/mfa_models/markets.py
antelope_reports/mfa_study/__init__.py
antelope_reports/mfa_study/dynamic_unit_study.py
antelope_reports/mfa_study/lc_mfa_study.py
antelope_reports/mfa_study/observed_mfa_study.py
antelope_reports/model_runner/__init__.py
antelope_reports/model_runner/components_mixin.py
antelope_reports/model_runner/lca_model_runner.py
antelope_reports-0.2.3.dist-info/METADATA
antelope_reports-0.2.3.dist-info/WHEEL
antelope_reports-0.2.3.dist-info/top_level.txt
antelope_reports-0.2.3.dist-info/RECORD
