Metadata-Version: 2.4
Name: antelope_reports
Version: 0.2.3
Summary: Tools for summarizing and visualizing LCA models in Antelope
Author-email: Brandon Kuczenski <brandon@scope3consulting.com>
License: BSD-3-Clause
Project-URL: Repository, https://github.com/AntelopeLCA/reports
Keywords: antelope,waterfall,bar chart,model runner,scenario,lca study
Classifier: Development Status :: 3 - Alpha
Classifier: Intended Audience :: Science/Research
Classifier: License :: OSI Approved :: BSD License
Classifier: Natural Language :: English
Classifier: Operating System :: OS Independent
Classifier: Programming Language :: Python :: 3
Classifier: Topic :: Scientific/Engineering
Requires-Python: >=3.6
Requires-Dist: antelope-foreground>=0.3.3
Requires-Dist: antelope-core>=0.3.3
Requires-Dist: synonym-dict>=0.2.4
Requires-Dist: pandas
Requires-Dist: matplotlib
Requires-Dist: pydot>=2.0.0
